{
  "data":{
    "extraDetails":{
      "quizTitle":"Fruit flashcard",
      "previousSet":"",
      "nextSet":null,
      "numberOfQuestion":"21",
      "keywords":"",
      "description":"",
      "url":"",
      "imageUrl":"",
      "referralLink":[]
    },
    "questions":[
      {
        "imageName":"/flashCard/fruits/apple.png",
        "qn":"Apple"
      },
      {
        "imageName":"/flashCard/fruits/apricot.png",
        "qn":"Apricot"
      },
      {
        "imageName":"/flashCard/fruits/avocado.png",
        "qn":"Avocado"
      },
      {
        "imageName":"/flashCard/fruits/banana.png",
        "qn":"Banana"
      },
      {
        "imageName":"/flashCard/fruits/cherry.png",
        "qn":"Cherry"
      },
      {
        "imageName":"/flashCard/fruits/coconut.png",
        "qn":"Coconut"
      },
      {
        "imageName":"/flashCard/fruits/custardapple.png",
        "qn":"Custard Apple"
      },
      {
        "imageName":"/flashCard/fruits/grapes.png",
        "qn":"Grapes"
      },
      {
        "imageName":"/flashCard/fruits/guava.png",
        "qn":"Guava"
      },
      {
        "imageName":"/flashCard/fruits/kiwi.png",
        "qn":"Kiwi"
      },
      {
        "imageName":"/flashCard/fruits/lime.png",
        "qn":"Lime"
      },
      {
        "imageName":"/flashCard/fruits/mango.png",
        "qn":"Mango"
      },
      {
        "imageName":"/flashCard/fruits/orange.png",
        "qn":"Orange"
      },
      {
        "imageName":"/flashCard/fruits/papaya.png",
        "qn":"Papaya"
      },
      {
        "imageName":"/flashCard/fruits/peach.png",
        "qn":"Peach"
      },
      {
        "imageName":"/flashCard/fruits/pear.png",
        "qn":"Pear"
      },
      {
        "imageName":"/flashCard/fruits/pineapple.png",
        "qn":"Pine Apple"
      },
      {
        "imageName":"/flashCard/fruits/plum.png",
        "qn":"Plum?"
      },
      {
        "imageName":"/flashCard/fruits/pomegranate.png",
        "qn":"Pomegranate"
      },
      {
        "imageName":"/flashCard/fruits/strawberry.png",
        "qn":"Strawberry"
      },
      {
        "imageName":"/flashCard/fruits/watermelon.png",
        "qn":"Watermelon"
      }

    ]
  }
}
